[
  {
    "purpose": "Main Events",
    "location": "Ballroom A"
  },
  {
    "purpose": "Blue Stage",
    "location": "Vendor Hall"
  },
  {
    "purpose": "Panel Room 1",
    "location": "Meeting Room 109"
  },
  {
    "purpose": "Panel Room 2",
    "location": "Meeting Room 119"
  },
  {
    "purpose": "Panel Room 3",
    "location": "Meeting Room 121"
  },
  {
    "purpose": "Creation Station",
    "location": "Meeting Room 116"
  },
  {
    "purpose": "Viewing Room 1",
    "location": "Meeting Room 111"
  },
  {
    "purpose": "Viewing Room 2",
    "location": "Meeting Room 114"
  },
  {
    "purpose": "Console Gaming",
    "location": "Vendor Hall"
  },
  {
    "purpose": "Tabletop Gaming",
    "location": "Vendor Hall"
  }
]